{
    "dataset": "Report(Bertelegni2023)",
    "gap_parameters": {
        "gap_type": "overlap",
        "perc": "50.0 %",
        "length": 24,
        "seed": 2025
    },
    "algorithm": "SoftImpute",
    "algorithm_parameters": {
        "max_rank": 3
    },
    "metrics": {
        "Missing value percentage": 1.7272104180945853,
        "Missing value percentage between 4 and 9": 0.546448087431694,
        "Mean absolute error": 0.1377944361983371,
        "Mean square error": 0.030269506524865847,
        "Root mean square error": 0.17398133958808873,
        "Mean relative error": 0.1088352924671969,
        "Euclidean Distance": 1.7046620270268096,
        "r2 score": 0.9650363880926728,
        "Execution Time": 0.3670918941497803
    },
    "vintage_score": {
        "original": {
            "Tmean_apr_sep": 20.354001429188713,
            "Tmin_aug_sep": 16.15245901639344,
            "prec_jun_sep": 125.0,
            "vintage_score": -4.14670757438347
        },
        "missing": {
            "Tmean_apr_sep": 20.353955891848095,
            "Tmin_aug_sep": 16.277049180327868,
            "prec_jun_sep": 125.0,
            "vintage_score": -4.197412933990904
        },
        "filled": {
            "Tmean_apr_sep": 20.31024855248074,
            "Tmin_aug_sep": 16.1911506559548,
            "prec_jun_sep": 124.92683365072676,
            "vintage_score": -3.933149996844435
        },
        "Deviation missing": 1.2227859982379665,
        "Deviation filled": 5.150051545913185,
        "Improvement": -3.9272655476752187
    }
}