{
    "dataset": "UCB1_lai_field_timeseries",
    "gap_parameters": {
        "gap_type": "custom_single",
        "seed": 2023
    },
    "algorithm": "Naive",
    "algorithm_parameters": {},
    "metrics": {
        "Missing value percentage": 14.015151515151516,
        "Mean absolute error": 0.23074395778703904,
        "Mean square error": 0.21109951385621073,
        "Root mean square error": 0.4594556712635189,
        "Mean relative error": 0.27497364005867914,
        "Euclidean Distance": 1.0273741135931276,
        "r2 score": 0.833335014364435,
        "Execution Time": 0.17089581489562988
    }
}